tfitpy/__init__.py
tfitpy/cli.py
tfitpy/config.py
tfitpy/data/biomart.py
tfitpy/data/hippie.py
tfitpy/data/stringdb.py
tfitpy/setup.py
tfitpy/utils.py
tfitpy-0.0.1.dist-info/METADATA
tfitpy-0.0.1.dist-info/WHEEL
tfitpy-0.0.1.dist-info/entry_points.txt
tfitpy-0.0.1.dist-info/licenses/LICENSE
tfitpy-0.0.1.dist-info/RECORD
